deen_api/__init__.py
deen_api/client.py
deen_api/exceptions.py
deen_api/models.py
deen_api_client-1.0.0.dist-info/licenses/LICENSE
examples/__init__.py
examples/hadith_example.py
tests/__init__.py
tests/test_client.py
deen_api_client-1.0.0.dist-info/METADATA
deen_api_client-1.0.0.dist-info/WHEEL
deen_api_client-1.0.0.dist-info/top_level.txt
deen_api_client-1.0.0.dist-info/RECORD
