Metadata-Version: 2.4
Name: deen-api-client
Version: 1.0.0
Summary: Python client for Deen API from Imaniro.com - Islamic resources API
Home-page: https://github.com/imaniro-tech/deen-api-python-client
Author: Imaniro pvt ltd
Author-email: info@imaniro.com
Project-URL: Documentation, https://github.com/imaniro-tech/deen-api-python-client
Project-URL: Source, https://github.com/imaniro-tech/deen-api-python-client
Project-URL: Tracker, https://github.com/imaniro-tech/deen-api-python-client/issues
Keywords: islamic,api,hadith,quran,dua,muslim
Classifier: Development Status :: 4 - Beta
Classifier: Intended Audience :: Developers
Classifier: License :: OSI Approved :: MIT License
Classifier: Operating System :: OS Independent
Classifier: Programming Language :: Python :: 3
Classifier: Programming Language :: Python :: 3.7
Classifier: Programming Language :: Python :: 3.8
Classifier: Programming Language :: Python :: 3.9
Classifier: Programming Language :: Python :: 3.10
Classifier: Programming Language :: Python :: 3.11
Classifier: Programming Language :: Python :: 3.12
Requires-Python: >=3.7
License-File: LICENSE
Requires-Dist: requests>=2.25.0
Requires-Dist: dataclasses>=0.6; python_version < "3.7"
Provides-Extra: dev
Requires-Dist: pytest>=6.0.0; extra == "dev"
Requires-Dist: requests-mock>=1.9.0; extra == "dev"
Requires-Dist: pytest-cov>=2.0.0; extra == "dev"
Dynamic: author
Dynamic: author-email
Dynamic: classifier
Dynamic: description
Dynamic: description-content-type
Dynamic: home-page
Dynamic: keywords
Dynamic: license-file
Dynamic: project-url
Dynamic: provides-extra
Dynamic: requires-dist
Dynamic: requires-python
Dynamic: summary
